tedective_etl/__init__.py
tedective_etl/currency/__init__.py
tedective_etl/currency/rates.json
tedective_etl/currency/update.py
tedective_etl/dedupe.py
tedective_etl/graph.py
tedective_etl/main.py
tedective_etl/schema/ocds.py
tedective_etl/search.py
tedective_etl/server.py
tedective_etl/ted_to_ocds/__init__.py
tedective_etl/ted_to_ocds/extractors.py
tedective_etl/ted_to_ocds/process.py
tedective_etl/ted_to_ocds/trackers.py
tedective_etl/ted_to_ocds/transform.py
tedective_etl/utils.py
tedective_etl-0.1.3.dist-info/METADATA
tedective_etl-0.1.3.dist-info/WHEEL
tedective_etl-0.1.3.dist-info/entry_points.txt
tedective_etl-0.1.3.dist-info/RECORD
