Metadata-Version: 2.1
Name: tedective-etl
Version: 0.1.3
Summary: The XML-to-OCDS parser for the TEDective project based on lxml
License: AGPL-3.0-or-later
Author: Free Software Foundation Europe e.V.
Author-email: tedective@fsfe.org
Requires-Python: >=3.10,<4.0
Classifier: License :: OSI Approved :: GNU Affero General Public License v3 or later (AGPLv3+)
Classifier: Programming Language :: Python :: 3
Classifier: Programming Language :: Python :: 3.10
Classifier: Programming Language :: Python :: 3.11
Classifier: Programming Language :: Python :: 3.12
Requires-Dist: datamodel-code-generator[http] (==0.22.1)
Requires-Dist: fingerprints (==1.1.1)
Requires-Dist: ftfy (==6.1.1)
Requires-Dist: jupyter (==1.0.0)
Requires-Dist: kuzu (==0.3.2)
Requires-Dist: luigi (==3.5.0)
Requires-Dist: lxml (==4.9.3)
Requires-Dist: meilisearch (==0.30.0)
Requires-Dist: orjson (==3.8.9)
Requires-Dist: orjsonl (==0.3.1)
Requires-Dist: pandas (==2.1.4)
Requires-Dist: phonenumbers (==8.13.18)
Requires-Dist: phonetics (==1.0.5)
Requires-Dist: pyarrow (==14.0.2)
Requires-Dist: pyicu (==2.12)
Requires-Dist: python-dateutil (==2.8.2)
Requires-Dist: rich (==13.5.2)
Requires-Dist: splink (==3.9.11)
Project-URL: Documentation, https://docs.tedective.org
Project-URL: Homepage, https://tedective.org
Project-URL: Repository, https://git.fsfe.org/TEDective/etl
